{
  "endpoint": "accounts_staking_payouts",
  "service": "sidecar",
  "scenario": "heavy_load",
  "hardware": "dedicated_server",
  "threads": 8,
  "connections": 100,
  "chain": "statemint",
  "rps": 2.12,
  "avg_latency_ms": 20941.80,
  "stdev_ms": 14228.48,
  "max_latency_ms": 118298.92,
  "min_latency_ms": 494.41,
  "p50_ms": 20600.82,
  "p75_ms": 23535.56,
  "p90_ms": 26539.65,
  "p95_ms": 32742.33,
  "p99_ms": 99045.48,
  "p999_ms": 118298.92,
  "req_sec_avg": 0.18,
  "req_sec_stdev": 0.42,
  "req_sec_max": 2.00,
  "errors_total": 36,
  "errors_status": 36,
  "errors_connect": 0,
  "errors_read": 0,
  "errors_write": 0,
  "errors_timeout": 0,
  "total_requests": 255,
  "duration_s": 120.06,
  "bytes": 343489,
  "transfer_per_sec": 2861.05,
  "run_number": 10,
  "total_runs": 10,
  "resources": {
    "session_id": "sidecar_accounts_staking_payouts_20260323_085402_754590",
    "start_rss_mb": 123.39,
    "peak_rss_mb": 2515.74,
    "end_rss_mb": 900.36,
    "delta_rss_mb": 776.97,
    "avg_cpu_pct": 108.4,
    "peak_cpu_pct": 209.8,
    "samples": 1320,
    "baseline_sec": 60,
    "cooldown_sec": 60
  }
}
