{
  "endpoint": "accounts_balance_info",
  "service": "polkadot-rest-api",
  "scenario": "medium_load",
  "hardware": "dedicated_server",
  "threads": 4,
  "connections": 50,
  "chain": "statemint",
  "rps": 1237.82,
  "avg_latency_ms": 39.34,
  "stdev_ms": 11.90,
  "max_latency_ms": 289.64,
  "min_latency_ms": 36.22,
  "p50_ms": 37.36,
  "p75_ms": 38.27,
  "p90_ms": 41.36,
  "p95_ms": 46.03,
  "p99_ms": 63.50,
  "p999_ms": 234.87,
  "req_sec_avg": 310.86,
  "req_sec_stdev": 36.42,
  "req_sec_max": 363.00,
  "errors_total": 0,
  "errors_status": 0,
  "errors_connect": 0,
  "errors_read": 0,
  "errors_write": 0,
  "errors_timeout": 0,
  "total_requests": 74318,
  "duration_s": 60.04,
  "bytes": 50541422,
  "transfer_per_sec": 841806.20,
  "run_number": 10,
  "total_runs": 10,
  "resources": {
    "session_id": "rest-api_accounts_balance_info_20260319_201151_59014",
    "start_rss_mb": 34.60,
    "peak_rss_mb": 273.53,
    "end_rss_mb": 271.15,
    "delta_rss_mb": 236.55,
    "avg_cpu_pct": 56.6,
    "peak_cpu_pct": 98.0,
    "samples": 720,
    "baseline_sec": 60,
    "cooldown_sec": 60
  }
}
