{
  "endpoint": "accounts_balance_info",
  "service": "polkadot-rest-api",
  "scenario": "stress_test",
  "hardware": "dedicated_server",
  "threads": 12,
  "connections": 200,
  "chain": "statemint",
  "rps": 711.19,
  "avg_latency_ms": 282.33,
  "stdev_ms": 186.13,
  "max_latency_ms": 1098.80,
  "min_latency_ms": 52.77,
  "p50_ms": 205.88,
  "p75_ms": 403.80,
  "p90_ms": 569.64,
  "p95_ms": 655.05,
  "p99_ms": 799.04,
  "p999_ms": 932.91,
  "req_sec_avg": 68.46,
  "req_sec_stdev": 50.39,
  "req_sec_max": 323.00,
  "errors_total": 0,
  "errors_status": 0,
  "errors_connect": 0,
  "errors_read": 0,
  "errors_write": 0,
  "errors_timeout": 0,
  "total_requests": 213428,
  "duration_s": 300.10,
  "bytes": 145145908,
  "transfer_per_sec": 483661.81,
  "run_number": 10,
  "total_runs": 10,
  "resources": {
    "session_id": "rest-api_accounts_balance_info_20260323_073239_688685",
    "start_rss_mb": 28.02,
    "peak_rss_mb": 3195.78,
    "end_rss_mb": 3192.63,
    "delta_rss_mb": 3164.61,
    "avg_cpu_pct": 136.3,
    "peak_cpu_pct": 290.0,
    "samples": 3240,
    "baseline_sec": 120,
    "cooldown_sec": 120
  }
}
