{
  "endpoint": "accounts_balance_info",
  "service": "polkadot-rest-api",
  "scenario": "medium_load",
  "hardware": "dedicated_server",
  "threads": 4,
  "connections": 50,
  "chain": "statemint",
  "rps": 1005.78,
  "avg_latency_ms": 48.11,
  "stdev_ms": 14.08,
  "max_latency_ms": 273.32,
  "min_latency_ms": 36.26,
  "p50_ms": 45.94,
  "p75_ms": 51.18,
  "p90_ms": 60.35,
  "p95_ms": 68.25,
  "p99_ms": 86.30,
  "p999_ms": 245.30,
  "req_sec_avg": 252.55,
  "req_sec_stdev": 46.24,
  "req_sec_max": 363.00,
  "errors_total": 0,
  "errors_status": 0,
  "errors_connect": 0,
  "errors_read": 0,
  "errors_write": 0,
  "errors_timeout": 0,
  "total_requests": 60394,
  "duration_s": 60.05,
  "bytes": 41072202,
  "transfer_per_sec": 684004.60,
  "run_number": 4,
  "total_runs": 10,
  "resources": {
    "session_id": "rest-api_accounts_balance_info_20260319_201151_59014",
    "start_rss_mb": 34.60,
    "peak_rss_mb": 273.53,
    "end_rss_mb": 271.15,
    "delta_rss_mb": 236.55,
    "avg_cpu_pct": 56.6,
    "peak_cpu_pct": 98.0,
    "samples": 720,
    "baseline_sec": 60,
    "cooldown_sec": 60
  }
}
