{
  "endpoint": "accounts_balance_info",
  "service": "sidecar",
  "scenario": "stress_test",
  "hardware": "dedicated_server",
  "threads": 12,
  "connections": 200,
  "chain": "statemint",
  "rps": 327.61,
  "avg_latency_ms": 590.75,
  "stdev_ms": 138.64,
  "max_latency_ms": 4118.59,
  "min_latency_ms": 38.85,
  "p50_ms": 579.81,
  "p75_ms": 596.02,
  "p90_ms": 618.95,
  "p95_ms": 640.51,
  "p99_ms": 864.17,
  "p999_ms": 2896.52,
  "req_sec_avg": 35.82,
  "req_sec_stdev": 31.30,
  "req_sec_max": 151.00,
  "errors_total": 0,
  "errors_status": 0,
  "errors_connect": 0,
  "errors_read": 0,
  "errors_write": 0,
  "errors_timeout": 0,
  "total_requests": 98290,
  "duration_s": 300.02,
  "bytes": 65369583,
  "transfer_per_sec": 217884.29,
  "run_number": 3,
  "total_runs": 10,
  "resources": {
    "session_id": "sidecar_accounts_balance_info_20260323_115217_928719",
    "start_rss_mb": 120.41,
    "peak_rss_mb": 909.25,
    "end_rss_mb": 218.51,
    "delta_rss_mb": 98.09,
    "avg_cpu_pct": 122.3,
    "peak_cpu_pct": 204.4,
    "samples": 3240,
    "baseline_sec": 120,
    "cooldown_sec": 120
  }
}
