{
  "endpoint": "pallets_storage",
  "service": "polkadot-rest-api",
  "scenario": "stress_test",
  "hardware": "dedicated_server",
  "threads": 12,
  "connections": 200,
  "chain": "statemint",
  "rps": 6349.18,
  "avg_latency_ms": 33.24,
  "stdev_ms": 28.46,
  "max_latency_ms": 652.12,
  "min_latency_ms": 26.35,
  "p50_ms": 28.24,
  "p75_ms": 29.88,
  "p90_ms": 33.28,
  "p95_ms": 41.15,
  "p99_ms": 185.61,
  "p999_ms": 387.47,
  "req_sec_avg": 532.31,
  "req_sec_stdev": 95.93,
  "req_sec_max": 646.00,
  "errors_total": 0,
  "errors_status": 0,
  "errors_connect": 0,
  "errors_read": 0,
  "errors_write": 0,
  "errors_timeout": 0,
  "total_requests": 1905033,
  "duration_s": 300.04,
  "bytes": 10661191528,
  "transfer_per_sec": 35532120.72,
  "run_number": 8,
  "total_runs": 10,
  "resources": {
    "session_id": "rest-api_pallets_storage_20260324_175605_1747846",
    "start_rss_mb": 27.92,
    "peak_rss_mb": 125.16,
    "end_rss_mb": 96.01,
    "delta_rss_mb": 68.09,
    "avg_cpu_pct": 144.5,
    "peak_cpu_pct": 264.2,
    "samples": 3240,
    "baseline_sec": 120,
    "cooldown_sec": 120
  }
}
