{
  "endpoint": "blocks_extrinsics",
  "service": "polkadot-rest-api",
  "scenario": "medium_load",
  "hardware": "dedicated_server",
  "threads": 4,
  "connections": 50,
  "chain": "statemint",
  "rps": 510.97,
  "avg_latency_ms": 94.17,
  "stdev_ms": 22.81,
  "max_latency_ms": 373.33,
  "min_latency_ms": 61.05,
  "p50_ms": 88.51,
  "p75_ms": 103.69,
  "p90_ms": 121.35,
  "p95_ms": 133.69,
  "p99_ms": 163.07,
  "p999_ms": 312.58,
  "req_sec_avg": 128.52,
  "req_sec_stdev": 27.43,
  "req_sec_max": 210.00,
  "errors_total": 0,
  "errors_status": 0,
  "errors_connect": 0,
  "errors_read": 0,
  "errors_write": 0,
  "errors_timeout": 0,
  "total_requests": 30679,
  "duration_s": 60.04,
  "bytes": 1687402854,
  "transfer_per_sec": 28104560.68,
  "run_number": 3,
  "total_runs": 10,
  "resources": {
    "session_id": "rest-api_blocks_extrinsics_20260320_070511_142886",
    "start_rss_mb": 34.84,
    "peak_rss_mb": 194.09,
    "end_rss_mb": 176.15,
    "delta_rss_mb": 141.31,
    "avg_cpu_pct": 362.1,
    "peak_cpu_pct": 551.7,
    "samples": 720,
    "baseline_sec": 60,
    "cooldown_sec": 60
  }
}
